botfinder/__init__.py
botfinder/bot_classifier.py
botfinder/cli.py
botfinder/config.py
botfinder/random_forest.joblib
botfinder/version.py
social_networks_bot_finder-1.2.4.dist-info/METADATA
social_networks_bot_finder-1.2.4.dist-info/WHEEL
social_networks_bot_finder-1.2.4.dist-info/dependency_links.txt
social_networks_bot_finder-1.2.4.dist-info/entry_points.txt
social_networks_bot_finder-1.2.4.dist-info/top_level.txt
social_networks_bot_finder-1.2.4.dist-info/RECORD
