Metadata-Version: 2.1
Name: social-networks-bot-finder
Version: 1.2.4
Summary: CLI tool to help detecting if a twitter account is a bot
Home-page: https://github.com/ambanum/social-networks-bot-finder
Author: Ambanum
License: UNKNOWN
Platform: UNKNOWN
Classifier: Development Status :: 3 - Alpha
Classifier: License :: OSI Approved :: GNU General Public License v3 or later (GPLv3+)
Classifier: Programming Language :: Python :: 3.8
Classifier: Programming Language :: Python :: 3.9
Requires-Python: ~=3.8
Requires-Dist: click (==8.0.3)
Requires-Dist: joblib (==1.1.0)
Requires-Dist: pandas (==1.3.5)
Requires-Dist: shap (==0.40.0)
Requires-Dist: scikit-learn (==0.24.2)
Requires-Dist: numpy (==1.21.5)
Provides-Extra: test
Requires-Dist: coverage ; extra == 'test'
